bitflyer/ord_status.py
bitflyer/order_book.py
bitflyer/rpc.py
bitflyer/socketio.py
bitflyer/ticker.py
bitflyer/trading.py
bitflyer_rt-2.26.dist-info/METADATA
bitflyer_rt-2.26.dist-info/WHEEL
bitflyer_rt-2.26.dist-info/top_level.txt
bitflyer_rt-2.26.dist-info/RECORD
